{
  "type": "B",
  "rank": 3,
  "rootPosetNodes": [
    {
      "id": "r001",
      "shortLabel": "a001",
      "label": "alpha[3]",
      "x": 240.0,
      "y": 460.0
    },
    {
      "id": "r010",
      "shortLabel": "a010",
      "label": "alpha[2]",
      "x": 410.0,
      "y": 460.0
    },
    {
      "id": "r100",
      "shortLabel": "a100",
      "label": "alpha[1]",
      "x": 580.0,
      "y": 460.0
    },
    {
      "id": "r011",
      "shortLabel": "a011",
      "label": "alpha[2] + alpha[3]",
      "x": 296.67,
      "y": 357.5
    },
    {
      "id": "r110",
      "shortLabel": "a110",
      "label": "alpha[1] + alpha[2]",
      "x": 523.33,
      "y": 357.5
    },
    {
      "id": "r012",
      "shortLabel": "a012",
      "label": "alpha[2] + 2*alpha[3]",
      "x": 296.67,
      "y": 255.0
    },
    {
      "id": "r111",
      "shortLabel": "a111",
      "label": "alpha[1] + alpha[2] + alpha[3]",
      "x": 523.33,
      "y": 255.0
    },
    {
      "id": "r112",
      "shortLabel": "a112",
      "label": "alpha[1] + alpha[2] + 2*alpha[3]",
      "x": 410.0,
      "y": 152.5
    },
    {
      "id": "r122",
      "shortLabel": "a122",
      "label": "alpha[1] + 2*alpha[2] + 2*alpha[3]",
      "x": 410.0,
      "y": 50.0
    }
  ],
  "rootPosetEdges": [
    [
      "r001",
      "r011"
    ],
    [
      "r010",
      "r011"
    ],
    [
      "r010",
      "r110"
    ],
    [
      "r100",
      "r110"
    ],
    [
      "r011",
      "r012"
    ],
    [
      "r011",
      "r111"
    ],
    [
      "r110",
      "r111"
    ],
    [
      "r012",
      "r112"
    ],
    [
      "r111",
      "r112"
    ],
    [
      "r112",
      "r122"
    ]
  ],
  "incompatible": {
    "r001": [
      "r011",
      "r012",
      "r111",
      "r112",
      "r122"
    ],
    "r010": [
      "r011",
      "r110",
      "r012",
      "r111",
      "r112",
      "r122"
    ],
    "r100": [
      "r110",
      "r111",
      "r112",
      "r122"
    ],
    "r011": [
      "r001",
      "r010",
      "r012",
      "r111",
      "r112",
      "r122"
    ],
    "r110": [
      "r010",
      "r100",
      "r111",
      "r112",
      "r122"
    ],
    "r012": [
      "r001",
      "r010",
      "r011",
      "r112",
      "r122"
    ],
    "r111": [
      "r001",
      "r010",
      "r100",
      "r011",
      "r110",
      "r112",
      "r122"
    ],
    "r112": [
      "r001",
      "r010",
      "r100",
      "r011",
      "r110",
      "r012",
      "r111",
      "r122"
    ],
    "r122": [
      "r001",
      "r010",
      "r100",
      "r011",
      "r110",
      "r012",
      "r111",
      "r112"
    ]
  },
  "lowerIdeals": {
    "alpha[2] + 2*alpha[3] | alpha[1] + 2*alpha[2] + 2*alpha[3] | alpha[1] + alpha[2] + alpha[3] | alpha[3] | alpha[2] + alpha[3] | alpha[1] + alpha[2] + 2*alpha[3]": {
      "complementRoots": [
        "alpha[2] + 2*alpha[3]",
        "alpha[1] + 2*alpha[2] + 2*alpha[3]",
        "alpha[1] + alpha[2] + alpha[3]",
        "alpha[3]",
        "alpha[2] + alpha[3]",
        "alpha[1] + alpha[2] + 2*alpha[3]"
      ],
      "smooth": true,
      "correspondingWord": "[1, 2, 1]",
      "examples": [
        "s_[1, s_2, s_1]"
      ],
      "irrepColumns": [
        "3.",
        "21.",
        "2.1",
        ".3",
        "1.2",
        "11.1",
        "111.",
        "1.11",
        ".21",
        ".111"
      ],
      "irrepRows": {
        "0": {
          "3.": 1,
          "2.1": 1,
          ".3": 1,
          "1.2": 1
        },
        "2": {
          "3.": 2,
          "2.1": 2,
          ".3": 2,
          "1.2": 2
        },
        "4": {
          "3.": 2,
          "2.1": 2,
          ".3": 2,
          "1.2": 2
        },
        "6": {
          "3.": 1,
          "2.1": 1,
          ".3": 1,
          "1.2": 1
        }
      },
      "iccColumns": [
        "7",
        "511(11)",
        "511",
        "331(11)",
        "331",
        "322",
        "31111(11)",
        "31111",
        "22111",
        "1111111"
      ],
      "iccRows": {
        "0": {
          "331(11)": 1,
          "331": 1
        },
        "2": {
          "331(11)": 2,
          "331": 2
        },
        "4": {
          "331(11)": 2,
          "331": 2
        },
        "6": {
          "331(11)": 1,
          "331": 1
        }
      },
      "doubleHColumns": [
        "111.",
        "11.1",
        "1.11",
        ".111",
        "21.",
        "1.2",
        "2.1",
        ".21",
        "3.",
        ".3"
      ],
      "doubleHRows": {
        "0": {
          "1.2": 1,
          "2.1": 1,
          "3.": 1,
          ".3": 1
        },
        "2": {
          "1.2": 2,
          "2.1": 2,
          "3.": 2,
          ".3": 2
        },
        "4": {
          "1.2": 2,
          "2.1": 2,
          "3.": 2,
          ".3": 2
        },
        "6": {
          "1.2": 1,
          "2.1": 1,
          "3.": 1,
          ".3": 1
        }
      }
    },
    "alpha[2] + 2*alpha[3] | alpha[1] + 2*alpha[2] + 2*alpha[3] | alpha[1] + alpha[2] + 2*alpha[3]": {
      "complementRoots": [
        "alpha[2] + 2*alpha[3]",
        "alpha[1] + 2*alpha[2] + 2*alpha[3]",
        "alpha[1] + alpha[2] + 2*alpha[3]"
      ],
      "smooth": true,
      "correspondingWord": "[1, 2, 3, 1, 2, 1]",
      "examples": [
        "s_[1, s_2, s_3, s_1, s_2, s_1]"
      ],
      "irrepColumns": [
        "3.",
        "21.",
        "2.1",
        ".3",
        "1.2",
        "11.1",
        "111.",
        "1.11",
        ".21",
        ".111"
      ],
      "irrepRows": {
        "0": {
          "3.": 1
        },
        "2": {
          "3.": 3,
          "21.": 1
        },
        "4": {
          "3.": 5,
          "21.": 3
        },
        "6": {
          "3.": 6,
          "21.": 4
        },
        "8": {
          "3.": 5,
          "21.": 3
        },
        "10": {
          "3.": 3,
          "21.": 1
        },
        "12": {
          "3.": 1
        }
      },
      "iccColumns": [
        "7",
        "511(11)",
        "511",
        "331(11)",
        "331",
        "322",
        "31111(11)",
        "31111",
        "22111",
        "1111111"
      ],
      "iccRows": {
        "0": {
          "7": 1
        },
        "2": {
          "7": 3,
          "511(11)": 1
        },
        "4": {
          "7": 5,
          "511(11)": 3
        },
        "6": {
          "7": 6,
          "511(11)": 4
        },
        "8": {
          "7": 5,
          "511(11)": 3
        },
        "10": {
          "7": 3,
          "511(11)": 1
        },
        "12": {
          "7": 1
        }
      },
      "doubleHColumns": [
        "111.",
        "11.1",
        "1.11",
        ".111",
        "21.",
        "1.2",
        "2.1",
        ".21",
        "3.",
        ".3"
      ],
      "doubleHRows": {
        "0": {
          "3.": 1
        },
        "2": {
          "21.": 1,
          "3.": 2
        },
        "4": {
          "21.": 3,
          "3.": 2
        },
        "6": {
          "21.": 4,
          "3.": 2
        },
        "8": {
          "21.": 3,
          "3.": 2
        },
        "10": {
          "21.": 1,
          "3.": 2
        },
        "12": {
          "3.": 1
        }
      }
    },
    "alpha[2] + 2*alpha[3] | alpha[1] + 2*alpha[2] + 2*alpha[3] | alpha[1] + alpha[2] + alpha[3] | alpha[1] + alpha[2] + 2*alpha[3]": {
      "complementRoots": [
        "alpha[2] + 2*alpha[3]",
        "alpha[1] + 2*alpha[2] + 2*alpha[3]",
        "alpha[1] + alpha[2] + alpha[3]",
        "alpha[1] + alpha[2] + 2*alpha[3]"
      ],
      "smooth": true,
      "correspondingWord": "[1, 2, 3, 1, 2], [2, 3, 1, 2, 1]",
      "examples": [
        "s_[1, s_2, s_3, s_1, s_2], s_[2, s_3, s_1, s_2, s_1]"
      ],
      "irrepColumns": [
        "3.",
        "21.",
        "2.1",
        ".3",
        "1.2",
        "11.1",
        "111.",
        "1.11",
        ".21",
        ".111"
      ],
      "irrepRows": {
        "0": {
          "3.": 1
        },
        "2": {
          "3.": 3,
          "21.": 1
        },
        "4": {
          "3.": 5,
          "21.": 3,
          "2.1": 1,
          ".3": 1,
          "1.2": 1
        },
        "6": {
          "3.": 5,
          "21.": 3,
          "2.1": 1,
          ".3": 1,
          "1.2": 1
        },
        "8": {
          "3.": 3,
          "21.": 1
        },
        "10": {
          "3.": 1
        }
      },
      "iccColumns": [
        "7",
        "511(11)",
        "511",
        "331(11)",
        "331",
        "322",
        "31111(11)",
        "31111",
        "22111",
        "1111111"
      ],
      "iccRows": {
        "0": {
          "7": 1
        },
        "2": {
          "7": 3,
          "511(11)": 1
        },
        "4": {
          "7": 4,
          "511(11)": 3,
          "331(11)": 1,
          "331": 1
        },
        "6": {
          "7": 4,
          "511(11)": 3,
          "331(11)": 1,
          "331": 1
        },
        "8": {
          "7": 3,
          "511(11)": 1
        },
        "10": {
          "7": 1
        }
      },
      "doubleHColumns": [
        "111.",
        "11.1",
        "1.11",
        ".111",
        "21.",
        "1.2",
        "2.1",
        ".21",
        "3.",
        ".3"
      ],
      "doubleHRows": {
        "0": {
          "3.": 1
        },
        "2": {
          "21.": 1,
          "3.": 2
        },
        "4": {
          "21.": 3,
          "1.2": 1,
          "2.1": 1,
          "3.": 2,
          ".3": 1
        },
        "6": {
          "21.": 3,
          "1.2": 1,
          "2.1": 1,
          "3.": 2,
          ".3": 1
        },
        "8": {
          "21.": 1,
          "3.": 2
        },
        "10": {
          "3.": 1
        }
      }
    },
    "alpha[2] + 2*alpha[3] | alpha[1] + 2*alpha[2] + 2*alpha[3] | alpha[1] + alpha[2] + alpha[3] | alpha[2] + alpha[3] | alpha[1] + alpha[2] + 2*alpha[3]": {
      "complementRoots": [
        "alpha[2] + 2*alpha[3]",
        "alpha[1] + 2*alpha[2] + 2*alpha[3]",
        "alpha[1] + alpha[2] + alpha[3]",
        "alpha[2] + alpha[3]",
        "alpha[1] + alpha[2] + 2*alpha[3]"
      ],
      "smooth": true,
      "correspondingWord": "[1, 2, 3, 1], [3, 1, 2, 1]",
      "examples": [
        "s_[1, s_2, s_3, s_1], s_[3, s_1, s_2, s_1]"
      ],
      "irrepColumns": [
        "3.",
        "21.",
        "2.1",
        ".3",
        "1.2",
        "11.1",
        "111.",
        "1.11",
        ".21",
        ".111"
      ],
      "irrepRows": {
        "0": {
          "3.": 1
        },
        "2": {
          "3.": 3,
          "21.": 1,
          "2.1": 1,
          ".3": 1,
          "1.2": 1
        },
        "4": {
          "3.": 4,
          "21.": 2,
          "2.1": 2,
          ".3": 2,
          "1.2": 2
        },
        "6": {
          "3.": 3,
          "21.": 1,
          "2.1": 1,
          ".3": 1,
          "1.2": 1
        },
        "8": {
          "3.": 1
        }
      },
      "iccColumns": [
        "7",
        "511(11)",
        "511",
        "331(11)",
        "331",
        "322",
        "31111(11)",
        "31111",
        "22111",
        "1111111"
      ],
      "iccRows": {
        "0": {
          "7": 1
        },
        "2": {
          "7": 2,
          "511(11)": 1,
          "331(11)": 1,
          "331": 1
        },
        "4": {
          "7": 2,
          "511(11)": 2,
          "331(11)": 2,
          "331": 2
        },
        "6": {
          "7": 2,
          "511(11)": 1,
          "331(11)": 1,
          "331": 1
        },
        "8": {
          "7": 1
        }
      },
      "doubleHColumns": [
        "111.",
        "11.1",
        "1.11",
        ".111",
        "21.",
        "1.2",
        "2.1",
        ".21",
        "3.",
        ".3"
      ],
      "doubleHRows": {
        "0": {
          "3.": 1
        },
        "2": {
          "21.": 1,
          "1.2": 1,
          "2.1": 1,
          "3.": 2,
          ".3": 1
        },
        "4": {
          "21.": 2,
          "1.2": 2,
          "2.1": 2,
          "3.": 2,
          ".3": 2
        },
        "6": {
          "21.": 1,
          "1.2": 1,
          "2.1": 1,
          "3.": 2,
          ".3": 1
        },
        "8": {
          "3.": 1
        }
      }
    },
    "alpha[2] + 2*alpha[3] | alpha[1] + alpha[2] | alpha[1] + 2*alpha[2] + 2*alpha[3] | alpha[1] + alpha[2] + alpha[3] | alpha[1] + alpha[2] + 2*alpha[3]": {
      "complementRoots": [
        "alpha[2] + 2*alpha[3]",
        "alpha[1] + alpha[2]",
        "alpha[1] + 2*alpha[2] + 2*alpha[3]",
        "alpha[1] + alpha[2] + alpha[3]",
        "alpha[1] + alpha[2] + 2*alpha[3]"
      ],
      "smooth": true,
      "correspondingWord": "[1, 2, 3, 2], [2, 3, 2, 1]",
      "examples": [
        "s_[1, s_2, s_3, s_2], s_[2, s_3, s_2, s_1]"
      ],
      "irrepColumns": [
        "3.",
        "21.",
        "2.1",
        ".3",
        "1.2",
        "11.1",
        "111.",
        "1.11",
        ".21",
        ".111"
      ],
      "irrepRows": {
        "0": {
          "3.": 1
        },
        "2": {
          "3.": 3,
          "21.": 2,
          "2.1": 1
        },
        "4": {
          "3.": 4,
          "21.": 4,
          "2.1": 2,
          ".3": 1,
          "1.2": 1,
          "11.1": 1,
          "111.": 1
        },
        "6": {
          "3.": 3,
          "21.": 2,
          "2.1": 1
        },
        "8": {
          "3.": 1
        }
      },
      "iccColumns": [
        "7",
        "511(11)",
        "511",
        "331(11)",
        "331",
        "322",
        "31111(11)",
        "31111",
        "22111",
        "1111111"
      ],
      "iccRows": {
        "0": {
          "7": 1
        },
        "2": {
          "7": 2,
          "511(11)": 2,
          "511": 1
        },
        "4": {
          "7": 2,
          "511(11)": 3,
          "511": 1,
          "331(11)": 1,
          "331": 1,
          "31111(11)": 1
        },
        "6": {
          "7": 2,
          "511(11)": 2,
          "511": 1
        },
        "8": {
          "7": 1
        }
      },
      "doubleHColumns": [
        "111.",
        "11.1",
        "1.11",
        ".111",
        "21.",
        "1.2",
        "2.1",
        ".21",
        "3.",
        ".3"
      ],
      "doubleHRows": {
        "0": {
          "3.": 1
        },
        "2": {
          "21.": 2,
          "2.1": 1,
          "3.": 1
        },
        "4": {
          "111.": 1,
          "11.1": 1,
          "21.": 2,
          "1.2": 1,
          "2.1": 1,
          "3.": 1,
          ".3": 1
        },
        "6": {
          "21.": 2,
          "2.1": 1,
          "3.": 1
        },
        "8": {
          "3.": 1
        }
      }
    },
    "alpha[2] + 2*alpha[3] | alpha[1] + alpha[2] | alpha[1] + 2*alpha[2] + 2*alpha[3] | alpha[1] + alpha[2] + alpha[3] | alpha[2] + alpha[3] | alpha[1] + alpha[2] + 2*alpha[3]": {
      "complementRoots": [
        "alpha[2] + 2*alpha[3]",
        "alpha[1] + alpha[2]",
        "alpha[1] + 2*alpha[2] + 2*alpha[3]",
        "alpha[1] + alpha[2] + alpha[3]",
        "alpha[2] + alpha[3]",
        "alpha[1] + alpha[2] + 2*alpha[3]"
      ],
      "smooth": true,
      "correspondingWord": "[1, 2, 3], [2, 3, 1], [3, 1, 2], [3, 2, 1]",
      "examples": [
        "s_[1, s_2, s_3], s_[2, s_3, s_1], s_[3, s_1, s_2], s_[3, s_2, s_1]"
      ],
      "irrepColumns": [
        "3.",
        "21.",
        "2.1",
        ".3",
        "1.2",
        "11.1",
        "111.",
        "1.11",
        ".21",
        ".111"
      ],
      "irrepRows": {
        "0": {
          "3.": 1
        },
        "2": {
          "3.": 3,
          "21.": 2,
          "2.1": 2,
          ".3": 1,
          "1.2": 2,
          "11.1": 1
        },
        "4": {
          "3.": 3,
          "21.": 2,
          "2.1": 2,
          ".3": 1,
          "1.2": 2,
          "11.1": 1
        },
        "6": {
          "3.": 1
        }
      },
      "iccColumns": [
        "7",
        "511(11)",
        "511",
        "331(11)",
        "331",
        "322",
        "31111(11)",
        "31111",
        "22111",
        "1111111"
      ],
      "iccRows": {
        "0": {
          "7": 1
        },
        "2": {
          "7": 1,
          "511(11)": 1,
          "331(11)": 1,
          "331": 1,
          "322": 1
        },
        "4": {
          "7": 1,
          "511(11)": 1,
          "331(11)": 1,
          "331": 1,
          "322": 1
        },
        "6": {
          "7": 1
        }
      },
      "doubleHColumns": [
        "111.",
        "11.1",
        "1.11",
        ".111",
        "21.",
        "1.2",
        "2.1",
        ".21",
        "3.",
        ".3"
      ],
      "doubleHRows": {
        "0": {
          "3.": 1
        },
        "2": {
          "11.1": 1,
          "21.": 2,
          "1.2": 2,
          "2.1": 1,
          "3.": 1,
          ".3": 1
        },
        "4": {
          "11.1": 1,
          "21.": 2,
          "1.2": 2,
          "2.1": 1,
          "3.": 1,
          ".3": 1
        },
        "6": {
          "3.": 1
        }
      }
    },
    "alpha[2] + 2*alpha[3] | alpha[1] + alpha[2] | alpha[1] + 2*alpha[2] + 2*alpha[3] | alpha[1] + alpha[2] + alpha[3] | alpha[3] | alpha[2] + alpha[3] | alpha[1] + alpha[2] + 2*alpha[3]": {
      "complementRoots": [
        "alpha[2] + 2*alpha[3]",
        "alpha[1] + alpha[2]",
        "alpha[1] + 2*alpha[2] + 2*alpha[3]",
        "alpha[1] + alpha[2] + alpha[3]",
        "alpha[3]",
        "alpha[2] + alpha[3]",
        "alpha[1] + alpha[2] + 2*alpha[3]"
      ],
      "smooth": true,
      "correspondingWord": "[1, 2], [2, 1]",
      "examples": [
        "s_[1, s_2], s_[2, s_1]"
      ],
      "irrepColumns": [
        "3.",
        "21.",
        "2.1",
        ".3",
        "1.2",
        "11.1",
        "111.",
        "1.11",
        ".21",
        ".111"
      ],
      "irrepRows": {
        "0": {
          "3.": 1,
          "2.1": 1,
          ".3": 1,
          "1.2": 1
        },
        "2": {
          "3.": 2,
          "21.": 1,
          "2.1": 3,
          ".3": 2,
          "1.2": 3,
          "11.1": 1,
          "1.11": 1,
          ".21": 1
        },
        "4": {
          "3.": 1,
          "2.1": 1,
          ".3": 1,
          "1.2": 1
        }
      },
      "iccColumns": [
        "7",
        "511(11)",
        "511",
        "331(11)",
        "331",
        "322",
        "31111(11)",
        "31111",
        "22111",
        "1111111"
      ],
      "iccRows": {
        "0": {
          "331(11)": 1,
          "331": 1
        },
        "2": {
          "331(11)": 1,
          "331": 1,
          "22111": 1
        },
        "4": {
          "331(11)": 1,
          "331": 1
        }
      },
      "doubleHColumns": [
        "111.",
        "11.1",
        "1.11",
        ".111",
        "21.",
        "1.2",
        "2.1",
        ".21",
        "3.",
        ".3"
      ],
      "doubleHRows": {
        "0": {
          "1.2": 1,
          "2.1": 1,
          "3.": 1,
          ".3": 1
        },
        "2": {
          "11.1": 1,
          "1.11": 1,
          "21.": 1,
          "1.2": 2,
          "2.1": 2,
          ".21": 1,
          "3.": 1,
          ".3": 1
        },
        "4": {
          "1.2": 1,
          "2.1": 1,
          "3.": 1,
          ".3": 1
        }
      }
    },
    "alpha[2] + 2*alpha[3] | alpha[1] + alpha[2] | alpha[1] + 2*alpha[2] + 2*alpha[3] | alpha[1] + alpha[2] + alpha[3] | alpha[2] | alpha[3] | alpha[2] + alpha[3] | alpha[1] + alpha[2] + 2*alpha[3]": {
      "complementRoots": [
        "alpha[2] + 2*alpha[3]",
        "alpha[1] + alpha[2]",
        "alpha[1] + 2*alpha[2] + 2*alpha[3]",
        "alpha[1] + alpha[2] + alpha[3]",
        "alpha[2]",
        "alpha[3]",
        "alpha[2] + alpha[3]",
        "alpha[1] + alpha[2] + 2*alpha[3]"
      ],
      "smooth": true,
      "correspondingWord": "[1]",
      "examples": [
        "s_[1]"
      ],
      "irrepColumns": [
        "3.",
        "21.",
        "2.1",
        ".3",
        "1.2",
        "11.1",
        "111.",
        "1.11",
        ".21",
        ".111"
      ],
      "irrepRows": {
        "0": {
          "3.": 1,
          "21.": 1,
          "2.1": 2,
          ".3": 1,
          "1.2": 2,
          "11.1": 1,
          "1.11": 1,
          ".21": 1
        },
        "2": {
          "3.": 1,
          "21.": 1,
          "2.1": 2,
          ".3": 1,
          "1.2": 2,
          "11.1": 1,
          "1.11": 1,
          ".21": 1
        }
      },
      "iccColumns": [
        "7",
        "511(11)",
        "511",
        "331(11)",
        "331",
        "322",
        "31111(11)",
        "31111",
        "22111",
        "1111111"
      ],
      "iccRows": {
        "0": {
          "22111": 1
        },
        "2": {
          "22111": 1
        }
      },
      "doubleHColumns": [
        "111.",
        "11.1",
        "1.11",
        ".111",
        "21.",
        "1.2",
        "2.1",
        ".21",
        "3.",
        ".3"
      ],
      "doubleHRows": {
        "0": {
          "11.1": 1,
          "1.11": 1,
          "21.": 1,
          "1.2": 1,
          "2.1": 1,
          ".21": 1
        },
        "2": {
          "11.1": 1,
          "1.11": 1,
          "21.": 1,
          "1.2": 1,
          "2.1": 1,
          ".21": 1
        }
      }
    },
    "alpha[1] + 2*alpha[2] + 2*alpha[3] | alpha[1] + alpha[2] + alpha[3] | alpha[1] + alpha[2] + 2*alpha[3]": {
      "complementRoots": [
        "alpha[1] + 2*alpha[2] + 2*alpha[3]",
        "alpha[1] + alpha[2] + alpha[3]",
        "alpha[1] + alpha[2] + 2*alpha[3]"
      ],
      "smooth": true,
      "correspondingWord": "[2, 3, 1, 2, 3, 2], [3, 2, 3, 1, 2, 1]",
      "examples": [
        "s_[2, s_3, s_1, s_2, s_3, s_2], s_[3, s_2, s_3, s_1, s_2, s_1]"
      ],
      "irrepColumns": [
        "3.",
        "21.",
        "2.1",
        ".3",
        "1.2",
        "11.1",
        "111.",
        "1.11",
        ".21",
        ".111"
      ],
      "irrepRows": {
        "0": {
          "3.": 1
        },
        "2": {
          "3.": 3
        },
        "4": {
          "3.": 5,
          "21.": 1,
          "2.1": 1,
          ".3": 1
        },
        "6": {
          "3.": 6,
          "21.": 2,
          "2.1": 2,
          ".3": 2
        },
        "8": {
          "3.": 5,
          "21.": 1,
          "2.1": 1,
          ".3": 1
        },
        "10": {
          "3.": 3
        },
        "12": {
          "3.": 1
        }
      },
      "iccColumns": [
        "7",
        "511(11)",
        "511",
        "331(11)",
        "331",
        "322",
        "31111(11)",
        "31111",
        "22111",
        "1111111"
      ],
      "iccRows": {
        "0": {
          "7": 1
        },
        "2": {
          "7": 3
        },
        "4": {
          "7": 4,
          "511(11)": 1,
          "511": 1,
          "331(11)": 1
        },
        "6": {
          "7": 4,
          "511(11)": 2,
          "511": 2,
          "331(11)": 2
        },
        "8": {
          "7": 4,
          "511(11)": 1,
          "511": 1,
          "331(11)": 1
        },
        "10": {
          "7": 3
        },
        "12": {
          "7": 1
        }
      },
      "doubleHColumns": [
        "111.",
        "11.1",
        "1.11",
        ".111",
        "21.",
        "1.2",
        "2.1",
        ".21",
        "3.",
        ".3"
      ],
      "doubleHRows": {
        "0": {
          "3.": 1
        },
        "2": {
          "3.": 3
        },
        "4": {
          "21.": 1,
          "2.1": 1,
          "3.": 4,
          ".3": 1
        },
        "6": {
          "21.": 2,
          "2.1": 2,
          "3.": 4,
          ".3": 2
        },
        "8": {
          "21.": 1,
          "2.1": 1,
          "3.": 4,
          ".3": 1
        },
        "10": {
          "3.": 3
        },
        "12": {
          "3.": 1
        }
      }
    },
    "alpha[2] + 2*alpha[3] | alpha[1] + alpha[2] | alpha[1] | alpha[1] + 2*alpha[2] + 2*alpha[3] | alpha[1] + alpha[2] + alpha[3] | alpha[1] + alpha[2] + 2*alpha[3]": {
      "complementRoots": [
        "alpha[2] + 2*alpha[3]",
        "alpha[1] + alpha[2]",
        "alpha[1]",
        "alpha[1] + 2*alpha[2] + 2*alpha[3]",
        "alpha[1] + alpha[2] + alpha[3]",
        "alpha[1] + alpha[2] + 2*alpha[3]"
      ],
      "smooth": true,
      "correspondingWord": "[2, 3, 2]",
      "examples": [
        "s_[2, s_3, s_2]"
      ],
      "irrepColumns": [
        "3.",
        "21.",
        "2.1",
        ".3",
        "1.2",
        "11.1",
        "111.",
        "1.11",
        ".21",
        ".111"
      ],
      "irrepRows": {
        "0": {
          "3.": 1,
          "21.": 1,
          "2.1": 1
        },
        "2": {
          "3.": 2,
          "21.": 3,
          "2.1": 2,
          "11.1": 1,
          "111.": 1
        },
        "4": {
          "3.": 2,
          "21.": 3,
          "2.1": 2,
          "11.1": 1,
          "111.": 1
        },
        "6": {
          "3.": 1,
          "21.": 1,
          "2.1": 1
        }
      },
      "iccColumns": [
        "7",
        "511(11)",
        "511",
        "331(11)",
        "331",
        "322",
        "31111(11)",
        "31111",
        "22111",
        "1111111"
      ],
      "iccRows": {
        "0": {
          "511(11)": 1,
          "511": 1
        },
        "2": {
          "511(11)": 2,
          "511": 2,
          "31111(11)": 1
        },
        "4": {
          "511(11)": 2,
          "511": 2,
          "31111(11)": 1
        },
        "6": {
          "511(11)": 1,
          "511": 1
        }
      },
      "doubleHColumns": [
        "111.",
        "11.1",
        "1.11",
        ".111",
        "21.",
        "1.2",
        "2.1",
        ".21",
        "3.",
        ".3"
      ],
      "doubleHRows": {
        "0": {
          "21.": 1,
          "2.1": 1
        },
        "2": {
          "111.": 1,
          "11.1": 1,
          "21.": 1,
          "2.1": 1
        },
        "4": {
          "111.": 1,
          "11.1": 1,
          "21.": 1,
          "2.1": 1
        },
        "6": {
          "21.": 1,
          "2.1": 1
        }
      }
    },
    "alpha[2] + 2*alpha[3] | alpha[1] + alpha[2] | alpha[1] | alpha[1] + 2*alpha[2] + 2*alpha[3] | alpha[1] + alpha[2] + alpha[3] | alpha[2] + alpha[3] | alpha[1] + alpha[2] + 2*alpha[3]": {
      "complementRoots": [
        "alpha[2] + 2*alpha[3]",
        "alpha[1] + alpha[2]",
        "alpha[1]",
        "alpha[1] + 2*alpha[2] + 2*alpha[3]",
        "alpha[1] + alpha[2] + alpha[3]",
        "alpha[2] + alpha[3]",
        "alpha[1] + alpha[2] + 2*alpha[3]"
      ],
      "smooth": true,
      "correspondingWord": "[2, 3], [3, 2]",
      "examples": [
        "s_[2, s_3], s_[3, s_2]"
      ],
      "irrepColumns": [
        "3.",
        "21.",
        "2.1",
        ".3",
        "1.2",
        "11.1",
        "111.",
        "1.11",
        ".21",
        ".111"
      ],
      "irrepRows": {
        "0": {
          "3.": 1,
          "21.": 1,
          "2.1": 1
        },
        "2": {
          "3.": 2,
          "21.": 3,
          "2.1": 3,
          ".3": 1,
          "1.2": 2,
          "11.1": 2,
          "111.": 1,
          "1.11": 1,
          ".21": 1
        },
        "4": {
          "3.": 1,
          "21.": 1,
          "2.1": 1
        }
      },
      "iccColumns": [
        "7",
        "511(11)",
        "511",
        "331(11)",
        "331",
        "322",
        "31111(11)",
        "31111",
        "22111",
        "1111111"
      ],
      "iccRows": {
        "0": {
          "511(11)": 1,
          "511": 1
        },
        "2": {
          "511(11)": 1,
          "511": 1,
          "31111(11)": 1,
          "22111": 1
        },
        "4": {
          "511(11)": 1,
          "511": 1
        }
      },
      "doubleHColumns": [
        "111.",
        "11.1",
        "1.11",
        ".111",
        "21.",
        "1.2",
        "2.1",
        ".21",
        "3.",
        ".3"
      ],
      "doubleHRows": {
        "0": {
          "21.": 1,
          "2.1": 1
        },
        "2": {
          "111.": 1,
          "11.1": 2,
          "1.11": 1,
          "21.": 1,
          "1.2": 1,
          "2.1": 1,
          ".21": 1
        },
        "4": {
          "21.": 1,
          "2.1": 1
        }
      }
    },
    "alpha[2] + 2*alpha[3] | alpha[1] + alpha[2] | alpha[1] | alpha[1] + 2*alpha[2] + 2*alpha[3] | alpha[1] + alpha[2] + alpha[3] | alpha[3] | alpha[2] + alpha[3] | alpha[1] + alpha[2] + 2*alpha[3]": {
      "complementRoots": [
        "alpha[2] + 2*alpha[3]",
        "alpha[1] + alpha[2]",
        "alpha[1]",
        "alpha[1] + 2*alpha[2] + 2*alpha[3]",
        "alpha[1] + alpha[2] + alpha[3]",
        "alpha[3]",
        "alpha[2] + alpha[3]",
        "alpha[1] + alpha[2] + 2*alpha[3]"
      ],
      "smooth": true,
      "correspondingWord": "[2]",
      "examples": [
        "s_[2]"
      ],
      "irrepColumns": [
        "3.",
        "21.",
        "2.1",
        ".3",
        "1.2",
        "11.1",
        "111.",
        "1.11",
        ".21",
        ".111"
      ],
      "irrepRows": {
        "0": {
          "3.": 1,
          "21.": 1,
          "2.1": 2,
          ".3": 1,
          "1.2": 2,
          "11.1": 1,
          "1.11": 1,
          ".21": 1
        },
        "2": {
          "3.": 1,
          "21.": 1,
          "2.1": 2,
          ".3": 1,
          "1.2": 2,
          "11.1": 1,
          "1.11": 1,
          ".21": 1
        }
      },
      "iccColumns": [
        "7",
        "511(11)",
        "511",
        "331(11)",
        "331",
        "322",
        "31111(11)",
        "31111",
        "22111",
        "1111111"
      ],
      "iccRows": {
        "0": {
          "22111": 1
        },
        "2": {
          "22111": 1
        }
      },
      "doubleHColumns": [
        "111.",
        "11.1",
        "1.11",
        ".111",
        "21.",
        "1.2",
        "2.1",
        ".21",
        "3.",
        ".3"
      ],
      "doubleHRows": {
        "0": {
          "11.1": 1,
          "1.11": 1,
          "21.": 1,
          "1.2": 1,
          "2.1": 1,
          ".21": 1
        },
        "2": {
          "11.1": 1,
          "1.11": 1,
          "21.": 1,
          "1.2": 1,
          "2.1": 1,
          ".21": 1
        }
      }
    },
    "alpha[1] + alpha[2] | alpha[1] + 2*alpha[2] + 2*alpha[3] | alpha[1] + alpha[2] + alpha[3] | alpha[1] + alpha[2] + 2*alpha[3]": {
      "complementRoots": [
        "alpha[1] + alpha[2]",
        "alpha[1] + 2*alpha[2] + 2*alpha[3]",
        "alpha[1] + alpha[2] + alpha[3]",
        "alpha[1] + alpha[2] + 2*alpha[3]"
      ],
      "smooth": true,
      "correspondingWord": "[3, 1, 2, 3, 2], [3, 2, 3, 2, 1]",
      "examples": [
        "s_[3, s_1, s_2, s_3, s_2], s_[3, s_2, s_3, s_2, s_1]"
      ],
      "irrepColumns": [
        "3.",
        "21.",
        "2.1",
        ".3",
        "1.2",
        "11.1",
        "111.",
        "1.11",
        ".21",
        ".111"
      ],
      "irrepRows": {
        "0": {
          "3.": 1
        },
        "2": {
          "3.": 3,
          "21.": 1,
          "2.1": 1
        },
        "4": {
          "3.": 4,
          "21.": 2,
          "2.1": 2,
          ".3": 1
        },
        "6": {
          "3.": 4,
          "21.": 2,
          "2.1": 2,
          ".3": 1
        },
        "8": {
          "3.": 3,
          "21.": 1,
          "2.1": 1
        },
        "10": {
          "3.": 1
        }
      },
      "iccColumns": [
        "7",
        "511(11)",
        "511",
        "331(11)",
        "331",
        "322",
        "31111(11)",
        "31111",
        "22111",
        "1111111"
      ],
      "iccRows": {
        "0": {
          "7": 1
        },
        "2": {
          "7": 2,
          "511(11)": 1,
          "511": 1
        },
        "4": {
          "7": 2,
          "511(11)": 2,
          "511": 2,
          "331(11)": 1
        },
        "6": {
          "7": 2,
          "511(11)": 2,
          "511": 2,
          "331(11)": 1
        },
        "8": {
          "7": 2,
          "511(11)": 1,
          "511": 1
        },
        "10": {
          "7": 1
        }
      },
      "doubleHColumns": [
        "111.",
        "11.1",
        "1.11",
        ".111",
        "21.",
        "1.2",
        "2.1",
        ".21",
        "3.",
        ".3"
      ],
      "doubleHRows": {
        "0": {
          "3.": 1
        },
        "2": {
          "21.": 1,
          "2.1": 1,
          "3.": 2
        },
        "4": {
          "21.": 2,
          "2.1": 2,
          "3.": 2,
          ".3": 1
        },
        "6": {
          "21.": 2,
          "2.1": 2,
          "3.": 2,
          ".3": 1
        },
        "8": {
          "21.": 1,
          "2.1": 1,
          "3.": 2
        },
        "10": {
          "3.": 1
        }
      }
    },
    "alpha[2] + 2*alpha[3] | alpha[1] + alpha[2] | alpha[1] + 2*alpha[2] + 2*alpha[3] | alpha[1] + alpha[2] + alpha[3] | alpha[2] | alpha[2] + alpha[3] | alpha[1] + alpha[2] + 2*alpha[3]": {
      "complementRoots": [
        "alpha[2] + 2*alpha[3]",
        "alpha[1] + alpha[2]",
        "alpha[1] + 2*alpha[2] + 2*alpha[3]",
        "alpha[1] + alpha[2] + alpha[3]",
        "alpha[2]",
        "alpha[2] + alpha[3]",
        "alpha[1] + alpha[2] + 2*alpha[3]"
      ],
      "smooth": true,
      "correspondingWord": "[3, 1]",
      "examples": [
        "s_[3, s_1]"
      ],
      "irrepColumns": [
        "3.",
        "21.",
        "2.1",
        ".3",
        "1.2",
        "11.1",
        "111.",
        "1.11",
        ".21",
        ".111"
      ],
      "irrepRows": {
        "0": {
          "3.": 1,
          "21.": 1,
          "2.1": 1,
          "1.2": 1,
          "11.1": 1
        },
        "2": {
          "3.": 2,
          "21.": 2,
          "2.1": 2,
          "1.2": 2,
          "11.1": 2
        },
        "4": {
          "3.": 1,
          "21.": 1,
          "2.1": 1,
          "1.2": 1,
          "11.1": 1
        }
      },
      "iccColumns": [
        "7",
        "511(11)",
        "511",
        "331(11)",
        "331",
        "322",
        "31111(11)",
        "31111",
        "22111",
        "1111111"
      ],
      "iccRows": {
        "0": {
          "322": 1
        },
        "2": {
          "322": 2
        },
        "4": {
          "322": 1
        }
      },
      "doubleHColumns": [
        "111.",
        "11.1",
        "1.11",
        ".111",
        "21.",
        "1.2",
        "2.1",
        ".21",
        "3.",
        ".3"
      ],
      "doubleHRows": {
        "0": {
          "11.1": 1,
          "21.": 1,
          "1.2": 1
        },
        "2": {
          "11.1": 2,
          "21.": 2,
          "1.2": 2
        },
        "4": {
          "11.1": 1,
          "21.": 1,
          "1.2": 1
        }
      }
    },
    "empty": {
      "complementRoots": [],
      "smooth": true,
      "correspondingWord": "[3, 2, 3, 1, 2, 3, 1, 2, 1]",
      "examples": [
        "s_[3, s_2, s_3, s_1, s_2, s_3, s_1, s_2, s_1]"
      ],
      "irrepColumns": [
        "3.",
        "21.",
        "2.1",
        ".3",
        "1.2",
        "11.1",
        "111.",
        "1.11",
        ".21",
        ".111"
      ],
      "irrepRows": {
        "0": {
          "3.": 1
        },
        "2": {
          "3.": 3
        },
        "4": {
          "3.": 5
        },
        "6": {
          "3.": 7
        },
        "8": {
          "3.": 8
        },
        "10": {
          "3.": 8
        },
        "12": {
          "3.": 7
        },
        "14": {
          "3.": 5
        },
        "16": {
          "3.": 3
        },
        "18": {
          "3.": 1
        }
      },
      "iccColumns": [
        "7",
        "511(11)",
        "511",
        "331(11)",
        "331",
        "322",
        "31111(11)",
        "31111",
        "22111",
        "1111111"
      ],
      "iccRows": {
        "0": {
          "7": 1
        },
        "2": {
          "7": 3
        },
        "4": {
          "7": 5
        },
        "6": {
          "7": 7
        },
        "8": {
          "7": 8
        },
        "10": {
          "7": 8
        },
        "12": {
          "7": 7
        },
        "14": {
          "7": 5
        },
        "16": {
          "7": 3
        },
        "18": {
          "7": 1
        }
      },
      "doubleHColumns": [
        "111.",
        "11.1",
        "1.11",
        ".111",
        "21.",
        "1.2",
        "2.1",
        ".21",
        "3.",
        ".3"
      ],
      "doubleHRows": {
        "0": {
          "3.": 1
        },
        "2": {
          "3.": 3
        },
        "4": {
          "3.": 5
        },
        "6": {
          "3.": 7
        },
        "8": {
          "3.": 8
        },
        "10": {
          "3.": 8
        },
        "12": {
          "3.": 7
        },
        "14": {
          "3.": 5
        },
        "16": {
          "3.": 3
        },
        "18": {
          "3.": 1
        }
      }
    },
    "alpha[1] + alpha[2] | alpha[1] | alpha[1] + 2*alpha[2] + 2*alpha[3] | alpha[1] + alpha[2] + alpha[3] | alpha[1] + alpha[2] + 2*alpha[3]": {
      "complementRoots": [
        "alpha[1] + alpha[2]",
        "alpha[1]",
        "alpha[1] + 2*alpha[2] + 2*alpha[3]",
        "alpha[1] + alpha[2] + alpha[3]",
        "alpha[1] + alpha[2] + 2*alpha[3]"
      ],
      "smooth": true,
      "correspondingWord": "[3, 2, 3, 2]",
      "examples": [
        "s_[3, s_2, s_3, s_2]"
      ],
      "irrepColumns": [
        "3.",
        "21.",
        "2.1",
        ".3",
        "1.2",
        "11.1",
        "111.",
        "1.11",
        ".21",
        ".111"
      ],
      "irrepRows": {
        "0": {
          "3.": 1,
          "21.": 1,
          "2.1": 1
        },
        "2": {
          "3.": 2,
          "21.": 2,
          "2.1": 2
        },
        "4": {
          "3.": 2,
          "21.": 2,
          "2.1": 2
        },
        "6": {
          "3.": 2,
          "21.": 2,
          "2.1": 2
        },
        "8": {
          "3.": 1,
          "21.": 1,
          "2.1": 1
        }
      },
      "iccColumns": [
        "7",
        "511(11)",
        "511",
        "331(11)",
        "331",
        "322",
        "31111(11)",
        "31111",
        "22111",
        "1111111"
      ],
      "iccRows": {
        "0": {
          "511(11)": 1,
          "511": 1
        },
        "2": {
          "511(11)": 2,
          "511": 2
        },
        "4": {
          "511(11)": 2,
          "511": 2
        },
        "6": {
          "511(11)": 2,
          "511": 2
        },
        "8": {
          "511(11)": 1,
          "511": 1
        }
      },
      "doubleHColumns": [
        "111.",
        "11.1",
        "1.11",
        ".111",
        "21.",
        "1.2",
        "2.1",
        ".21",
        "3.",
        ".3"
      ],
      "doubleHRows": {
        "0": {
          "21.": 1,
          "2.1": 1
        },
        "2": {
          "21.": 2,
          "2.1": 2
        },
        "4": {
          "21.": 2,
          "2.1": 2
        },
        "6": {
          "21.": 2,
          "2.1": 2
        },
        "8": {
          "21.": 1,
          "2.1": 1
        }
      }
    },
    "alpha[2] + 2*alpha[3] | alpha[1] + alpha[2] | alpha[1] | alpha[1] + 2*alpha[2] + 2*alpha[3] | alpha[1] + alpha[2] + alpha[3] | alpha[2] | alpha[2] + alpha[3] | alpha[1] + alpha[2] + 2*alpha[3]": {
      "complementRoots": [
        "alpha[2] + 2*alpha[3]",
        "alpha[1] + alpha[2]",
        "alpha[1]",
        "alpha[1] + 2*alpha[2] + 2*alpha[3]",
        "alpha[1] + alpha[2] + alpha[3]",
        "alpha[2]",
        "alpha[2] + alpha[3]",
        "alpha[1] + alpha[2] + 2*alpha[3]"
      ],
      "smooth": true,
      "correspondingWord": "[3]",
      "examples": [
        "s_[3]"
      ],
      "irrepColumns": [
        "3.",
        "21.",
        "2.1",
        ".3",
        "1.2",
        "11.1",
        "111.",
        "1.11",
        ".21",
        ".111"
      ],
      "irrepRows": {
        "0": {
          "3.": 1,
          "21.": 2,
          "2.1": 2,
          "1.2": 1,
          "11.1": 2,
          "111.": 1,
          "1.11": 1
        },
        "2": {
          "3.": 1,
          "21.": 2,
          "2.1": 2,
          "1.2": 1,
          "11.1": 2,
          "111.": 1,
          "1.11": 1
        }
      },
      "iccColumns": [
        "7",
        "511(11)",
        "511",
        "331(11)",
        "331",
        "322",
        "31111(11)",
        "31111",
        "22111",
        "1111111"
      ],
      "iccRows": {
        "0": {
          "31111(11)": 1,
          "31111": 1
        },
        "2": {
          "31111(11)": 1,
          "31111": 1
        }
      },
      "doubleHColumns": [
        "111.",
        "11.1",
        "1.11",
        ".111",
        "21.",
        "1.2",
        "2.1",
        ".21",
        "3.",
        ".3"
      ],
      "doubleHRows": {
        "0": {
          "111.": 1,
          "11.1": 2,
          "1.11": 1
        },
        "2": {
          "111.": 1,
          "11.1": 2,
          "1.11": 1
        }
      }
    },
    "alpha[2] + 2*alpha[3] | alpha[1] + alpha[2] | alpha[1] | alpha[1] + 2*alpha[2] + 2*alpha[3] | alpha[1] + alpha[2] + alpha[3] | alpha[2] | alpha[3] | alpha[2] + alpha[3] | alpha[1] + alpha[2] + 2*alpha[3]": {
      "complementRoots": [
        "alpha[2] + 2*alpha[3]",
        "alpha[1] + alpha[2]",
        "alpha[1]",
        "alpha[1] + 2*alpha[2] + 2*alpha[3]",
        "alpha[1] + alpha[2] + alpha[3]",
        "alpha[2]",
        "alpha[3]",
        "alpha[2] + alpha[3]",
        "alpha[1] + alpha[2] + 2*alpha[3]"
      ],
      "smooth": true,
      "correspondingWord": "[]",
      "examples": [
        "s_[]"
      ],
      "irrepColumns": [
        "3.",
        "21.",
        "2.1",
        ".3",
        "1.2",
        "11.1",
        "111.",
        "1.11",
        ".21",
        ".111"
      ],
      "irrepRows": {
        "0": {
          "3.": 1,
          "21.": 2,
          "2.1": 3,
          ".3": 1,
          "1.2": 3,
          "11.1": 3,
          "111.": 1,
          "1.11": 3,
          ".21": 2,
          ".111": 1
        }
      },
      "iccColumns": [
        "7",
        "511(11)",
        "511",
        "331(11)",
        "331",
        "322",
        "31111(11)",
        "31111",
        "22111",
        "1111111"
      ],
      "iccRows": {
        "0": {
          "1111111": 1
        }
      },
      "doubleHColumns": [
        "111.",
        "11.1",
        "1.11",
        ".111",
        "21.",
        "1.2",
        "2.1",
        ".21",
        "3.",
        ".3"
      ],
      "doubleHRows": {
        "0": {
          "111.": 1,
          "11.1": 3,
          "1.11": 3,
          ".111": 1
        }
      }
    }
  }
}